[
  {
    "age": 42,
    "age_rank": 0,
    "agegroup": "40-49",
    "bib": "339",
    "city": "Blue Springs",
    "drilldown": 0,
    "firstname": "Chad",
    "formattime": "5:24:21",
    "gender": "M",
    "gender_place": 1,
    "identgender": null,
    "lastname": "Wooderson",
    "participant_id": 28845,
    "photo_count": 0,
    "place": 1,
    "prior_count": 0,
    "race_count": 0,
    "runner_rank": 76.35,
    "state": "MO",
    "status": 1,
    "time": "19461000"
  },
  {
    "age": 53,
    "age_rank": 0,
    "agegroup": "50-59",
    "bib": "336",
    "city": "Tulsa",
    "drilldown": 0,
    "firstname": "Jack",
    "formattime": "5:39:41",
    "gender": "M",
    "gender_place": 2,
    "identgender": null,
    "lastname": "Jones",
    "participant_id": 777907,
    "photo_count": 0,
    "place": 2,
    "prior_count": 0,
    "race_count": 0,
    "runner_rank": 73.5,
    "state": "OK",
    "status": 1,
    "time": "20381000"
  },
  {
    "age": 34,
    "age_rank": 0,
    "agegroup": "30-39",
    "bib": "303",
    "city": "Manhattan",
    "drilldown": 0,
    "firstname": "Nate",
    "formattime": "5:50:50",
    "gender": "M",
    "gender_place": 3,
    "identgender": null,
    "lastname": "Birkhead",
    "participant_id": 1317472,
    "photo_count": 0,
    "place": 3,
    "prior_count": 0,
    "race_count": 0,
    "runner_rank": 90.4,
    "state": "KS",
    "status": 1,
    "time": "21050000"
  },
  {
    "age": 50,
    "age_rank": 0,
    "agegroup": "50-59",
    "bib": "338",
    "city": "Kansas City",
    "drilldown": 0,
    "firstname": "Albert",
    "formattime": "6:02:00",
    "gender": "M",
    "gender_place": 4,
    "identgender": null,
    "lastname": "Mauro",
    "participant_id": 512225,
    "photo_count": 0,
    "place": 4,
    "prior_count": 0,
    "race_count": 0,
    "runner_rank": 76.69,
    "state": "MO",
    "status": 1,
    "time": "21720000"
  },
  {
    "age": 33,
    "age_rank": 0,
    "agegroup": "30-39",
    "bib": "321",
    "city": "Tulsa",
    "drilldown": 0,
    "firstname": "Philip",
    "formattime": "6:13:32",
    "gender": "M",
    "gender_place": 5,
    "identgender": null,
    "lastname": "Berry",
    "participant_id": 674064,
    "photo_count": 0,
    "place": 5,
    "prior_count": 0,
    "race_count": 0,
    "runner_rank": 68.4,
    "state": "OK",
    "status": 1,
    "time": "22412000"
  },
  {
    "age": 52,
    "age_rank": 0,
    "agegroup": "50-59",
    "bib": "315",
    "city": "Baldwin City",
    "drilldown": 0,
    "firstname": "Michael",
    "formattime": "6:21:24",
    "gender": "M",
    "gender_place": 6,
    "identgender": null,
    "lastname": "Miley",
    "participant_id": 558038,
    "photo_count": 0,
    "place": 6,
    "prior_count": 0,
    "race_count": 0,
    "runner_rank": 71.53,
    "state": "KS",
    "status": 1,
    "time": "22884000"
  },
  {
    "age": 45,
    "age_rank": 0,
    "agegroup": "40-49",
    "bib": "318",
    "city": "Lecompton",
    "drilldown": 0,
    "firstname": "Ami",
    "formattime": "6:26:07",
    "gender": "F",
    "gender_place": 1,
    "identgender": null,
    "lastname": "Hyten",
    "participant_id": 2038898,
    "photo_count": 0,
    "place": 7,
    "prior_count": 0,
    "race_count": 0,
    "runner_rank": 74.82,
    "state": "KS",
    "status": 1,
    "time": "23167000"
  },
  {
    "age": 47,
    "age_rank": 0,
    "agegroup": "40-49",
    "bib": "309",
    "city": "Lees Summit",
    "drilldown": 0,
    "firstname": "Daron",
    "formattime": "6:34:41",
    "gender": "M",
    "gender_place": 7,
    "identgender": null,
    "lastname": "Pratt",
    "participant_id": 756665,
    "photo_count": 0,
    "place": 8,
    "prior_count": 0,
    "race_count": 0,
    "runner_rank": 76.45,
    "state": "MO",
    "status": 1,
    "time": "23681000"
  },
  {
    "age": 48,
    "age_rank": 0,
    "agegroup": "40-49",
    "bib": "337",
    "city": "Omaha",
    "drilldown": 0,
    "firstname": "Mark",
    "formattime": "6:42:27",
    "gender": "M",
    "gender_place": 8,
    "identgender": null,
    "lastname": "Nygaard",
    "participant_id": 980432,
    "photo_count": 0,
    "place": 9,
    "prior_count": 0,
    "race_count": 0,
    "runner_rank": 80.47,
    "state": "NE",
    "status": 1,
    "time": "24147000"
  },
  {
    "age": 60,
    "age_rank": 0,
    "agegroup": "60-69",
    "bib": "313",
    "city": "Lawrence",
    "drilldown": 0,
    "firstname": "Gary",
    "formattime": "6:53:48",
    "gender": "M",
    "gender_place": 9,
    "identgender": null,
    "lastname": "Henry",
    "participant_id": 6314,
    "photo_count": 0,
    "place": 10,
    "prior_count": 0,
    "race_count": 0,
    "runner_rank": 67.04,
    "state": "KS",
    "status": 1,
    "time": "24828000"
  },
  {
    "age": 57,
    "age_rank": 0,
    "agegroup": "50-59",
    "bib": "330",
    "city": "Shawnee",
    "drilldown": 0,
    "firstname": "Stuart",
    "formattime": "6:53:49",
    "gender": "M",
    "gender_place": 10,
    "identgender": null,
    "lastname": "Johnson",
    "participant_id": 4071,
    "photo_count": 0,
    "place": 11,
    "prior_count": 0,
    "race_count": 0,
    "runner_rank": 71.5,
    "state": "KS",
    "status": 1,
    "time": "24829000"
  },
  {
    "age": 37,
    "age_rank": 0,
    "agegroup": "30-39",
    "bib": "340",
    "city": "Olathe",
    "drilldown": 0,
    "firstname": "Brooke",
    "formattime": "6:58:52",
    "gender": "F",
    "gender_place": 2,
    "identgender": null,
    "lastname": "Watson",
    "participant_id": 1317383,
    "photo_count": 0,
    "place": 12,
    "prior_count": 0,
    "race_count": 0,
    "runner_rank": 94.34,
    "state": "KS",
    "status": 1,
    "time": "25132000"
  },
  {
    "age": 49,
    "age_rank": 0,
    "agegroup": "40-49",
    "bib": "312",
    "city": "Kansas City",
    "drilldown": 0,
    "firstname": "Todd",
    "formattime": "6:58:53",
    "gender": "M",
    "gender_place": 11,
    "identgender": null,
    "lastname": "Chandler",
    "participant_id": 1024723,
    "photo_count": 0,
    "place": 13,
    "prior_count": 0,
    "race_count": 0,
    "runner_rank": 65.04,
    "state": "MO",
    "status": 1,
    "time": "25133000"
  },
  {
    "age": 23,
    "age_rank": 0,
    "agegroup": "20-29",
    "bib": "329",
    "city": "Stilwell",
    "drilldown": 0,
    "firstname": "Gabrie",
    "formattime": "7:09:17",
    "gender": "F",
    "gender_place": 3,
    "identgender": null,
    "lastname": "Burriss",
    "participant_id": 1317471,
    "photo_count": 0,
    "place": 14,
    "prior_count": 0,
    "race_count": 0,
    "runner_rank": 82.95,
    "state": "KS",
    "status": 1,
    "time": "25757000"
  },
  {
    "age": 52,
    "age_rank": 0,
    "agegroup": "50-59",
    "bib": "328",
    "city": "Lawrence",
    "drilldown": 0,
    "firstname": "Paul",
    "formattime": "7:14:43",
    "gender": "M",
    "gender_place": 12,
    "identgender": null,
    "lastname": "Endacott",
    "participant_id": 532078,
    "photo_count": 0,
    "place": 15,
    "prior_count": 0,
    "race_count": 0,
    "runner_rank": 63.93,
    "state": "KS",
    "status": 1,
    "time": "26083000"
  },
  {
    "age": 43,
    "age_rank": 0,
    "agegroup": "40-49",
    "bib": "324",
    "city": "Tulsa",
    "drilldown": 0,
    "firstname": "Eva",
    "formattime": "7:15:18",
    "gender": "F",
    "gender_place": 4,
    "identgender": null,
    "lastname": "Jones",
    "participant_id": 1188505,
    "photo_count": 0,
    "place": 16,
    "prior_count": 0,
    "race_count": 0,
    "runner_rank": 62.16,
    "state": "OK",
    "status": 1,
    "time": "26118000"
  },
  {
    "age": 51,
    "age_rank": 0,
    "agegroup": "50-59",
    "bib": "333",
    "city": "Wichita",
    "drilldown": 0,
    "firstname": "Carlos",
    "formattime": "7:21:08",
    "gender": "M",
    "gender_place": 13,
    "identgender": null,
    "lastname": "Rodriguez",
    "participant_id": 250066,
    "photo_count": 0,
    "place": 17,
    "prior_count": 0,
    "race_count": 0,
    "runner_rank": 66.44,
    "state": "KS",
    "status": 1,
    "time": "26468000"
  },
  {
    "age": 32,
    "age_rank": 0,
    "agegroup": "30-39",
    "bib": "320",
    "city": "Lawrence",
    "drilldown": 0,
    "firstname": "Christian",
    "formattime": "7:22:03",
    "gender": "M",
    "gender_place": 14,
    "identgender": null,
    "lastname": "Beer",
    "participant_id": 1096724,
    "photo_count": 0,
    "place": 18,
    "prior_count": 0,
    "race_count": 0,
    "runner_rank": 71.05,
    "state": "KS",
    "status": 1,
    "time": "26523000"
  },
  {
    "age": 44,
    "age_rank": 0,
    "agegroup": "40-49",
    "bib": "322",
    "city": "Lees Summit",
    "drilldown": 0,
    "firstname": "Bianca",
    "formattime": "7:27:04",
    "gender": "F",
    "gender_place": 5,
    "identgender": null,
    "lastname": "Sullivan",
    "participant_id": 1024739,
    "photo_count": 0,
    "place": 19,
    "prior_count": 0,
    "race_count": 0,
    "runner_rank": 61.76,
    "state": "MO",
    "status": 1,
    "time": "26824000"
  },
  {
    "age": 58,
    "age_rank": 0,
    "agegroup": "50-59",
    "bib": "310",
    "city": "Indianapolis",
    "drilldown": 0,
    "firstname": "Daniel",
    "formattime": "7:41:42",
    "gender": "M",
    "gender_place": 15,
    "identgender": null,
    "lastname": "Sliva",
    "participant_id": 241112,
    "photo_count": 0,
    "place": 20,
    "prior_count": 0,
    "race_count": 0,
    "runner_rank": 60.44,
    "state": "IN",
    "status": 1,
    "time": "27702000"
  },
  {
    "age": 36,
    "age_rank": 0,
    "agegroup": "30-39",
    "bib": "307",
    "city": "Wichita",
    "drilldown": 0,
    "firstname": "Kristy",
    "formattime": "7:50:48",
    "gender": "F",
    "gender_place": 6,
    "identgender": null,
    "lastname": "Clark",
    "participant_id": 1161908,
    "photo_count": 0,
    "place": 21,
    "prior_count": 0,
    "race_count": 0,
    "runner_rank": 72.81,
    "state": "KS",
    "status": 1,
    "time": "28248000"
  },
  {
    "age": 31,
    "age_rank": 0,
    "agegroup": "30-39",
    "bib": "306",
    "city": "Eudora",
    "drilldown": 0,
    "firstname": "Tyler",
    "formattime": "8:04:22",
    "gender": "M",
    "gender_place": 16,
    "identgender": null,
    "lastname": "Cleveland",
    "participant_id": 1317473,
    "photo_count": 0,
    "place": 22,
    "prior_count": 0,
    "race_count": 0,
    "runner_rank": 66.96,
    "state": "KS",
    "status": 1,
    "time": "29062000"
  },
  {
    "age": 35,
    "age_rank": 0,
    "agegroup": "30-39",
    "bib": "327",
    "city": "Wichita",
    "drilldown": 0,
    "firstname": "Krystle",
    "formattime": "8:05:49",
    "gender": "F",
    "gender_place": 7,
    "identgender": null,
    "lastname": "Dalke",
    "participant_id": 353213,
    "photo_count": 0,
    "place": 23,
    "prior_count": 0,
    "race_count": 0,
    "runner_rank": 77.01,
    "state": "KS",
    "status": 1,
    "time": "29149000"
  },
  {
    "age": 36,
    "age_rank": 0,
    "agegroup": "30-39",
    "bib": "316",
    "city": "Derby",
    "drilldown": 0,
    "firstname": "Cody",
    "formattime": "8:05:49",
    "gender": "M",
    "gender_place": 17,
    "identgender": null,
    "lastname": "Chitwood",
    "participant_id": 586377,
    "photo_count": 0,
    "place": 23,
    "prior_count": 0,
    "race_count": 0,
    "runner_rank": 61.52,
    "state": "KS",
    "status": 1,
    "time": "29149000"
  },
  {
    "age": 56,
    "age_rank": 0,
    "agegroup": "50-59",
    "bib": "326",
    "city": "Bartlesville",
    "drilldown": 0,
    "firstname": "Jana",
    "formattime": "8:19:47",
    "gender": "F",
    "gender_place": 8,
    "identgender": null,
    "lastname": "Graham",
    "participant_id": 548742,
    "photo_count": 0,
    "place": 24,
    "prior_count": 0,
    "race_count": 0,
    "runner_rank": 70.89,
    "state": "OK",
    "status": 1,
    "time": "29987000"
  },
  {
    "age": 27,
    "age_rank": 0,
    "agegroup": "20-29",
    "bib": "334",
    "city": "Bartlesville",
    "drilldown": 0,
    "firstname": "Marie",
    "formattime": "8:19:48",
    "gender": "F",
    "gender_place": 9,
    "identgender": null,
    "lastname": "Polick",
    "participant_id": 1106896,
    "photo_count": 0,
    "place": 25,
    "prior_count": 0,
    "race_count": 0,
    "runner_rank": 66.8,
    "state": "OK",
    "status": 1,
    "time": "29988000"
  },
  {
    "age": 52,
    "age_rank": 0,
    "agegroup": "50-59",
    "bib": "325",
    "city": "Dewey",
    "drilldown": 0,
    "firstname": "Krystal",
    "formattime": "8:19:53",
    "gender": "F",
    "gender_place": 10,
    "identgender": null,
    "lastname": "Brown",
    "participant_id": 423560,
    "photo_count": 0,
    "place": 26,
    "prior_count": 0,
    "race_count": 0,
    "runner_rank": 75.04,
    "state": "OK",
    "status": 1,
    "time": "29993000"
  },
  {
    "age": 33,
    "age_rank": 0,
    "agegroup": "30-39",
    "bib": "304",
    "city": "Lawrence",
    "drilldown": 0,
    "firstname": "Jordan",
    "formattime": "8:48:38",
    "gender": "F",
    "gender_place": 11,
    "identgender": null,
    "lastname": "Shrack",
    "participant_id": 1045148,
    "photo_count": 0,
    "place": 27,
    "prior_count": 0,
    "race_count": 0,
    "runner_rank": 77.03,
    "state": "KS",
    "status": 1,
    "time": "31718000"
  },
  {
    "age": 40,
    "age_rank": 0,
    "agegroup": "40-49",
    "bib": "305",
    "city": "Lawrence",
    "drilldown": 0,
    "firstname": "Trudi",
    "formattime": "8:48:38",
    "gender": "F",
    "gender_place": 11,
    "identgender": null,
    "lastname": "Chavez",
    "participant_id": 868393,
    "photo_count": 0,
    "place": 27,
    "prior_count": 0,
    "race_count": 0,
    "runner_rank": 65.19,
    "state": "KS",
    "status": 1,
    "time": "31718000"
  },
  {
    "age": 75,
    "age_rank": 0,
    "agegroup": "70+",
    "bib": "335",
    "city": "Torrance",
    "drilldown": 0,
    "firstname": "Russell",
    "formattime": "11:28:34",
    "gender": "M",
    "gender_place": 18,
    "identgender": null,
    "lastname": "Cheney",
    "participant_id": 24978,
    "photo_count": 0,
    "place": 28,
    "prior_count": 0,
    "race_count": 0,
    "runner_rank": 48.23,
    "state": "CA",
    "status": 1,
    "time": "41314000"
  }
]
